tnmk_ensae/__init__.py
tnmk_ensae/main.py
tnmk_ensae-1.0.dist-info/LICENSE.txt
tnmk_ensae-1.0.dist-info/METADATA
tnmk_ensae-1.0.dist-info/WHEEL
tnmk_ensae-1.0.dist-info/top_level.txt
tnmk_ensae-1.0.dist-info/RECORD
